CONTRIBUTING.md
LICENSE
MANIFEST.in
Makefile
README.md
pyproject.toml
setup.py
docs/.buildinfo
docs/CONTRIBUTING.html
docs/Makefile
docs/README.html
docs/conf.py
docs/genindex.html
docs/index.html
docs/index.rst
docs/make.bat
docs/objects.inv
docs/search.html
docs/searchindex.js
docs/.doctrees/CONTRIBUTING.doctree
docs/.doctrees/README.doctree
docs/.doctrees/environment.pickle
docs/.doctrees/index.doctree
docs/.doctrees/.github/ISSUE_TEMPLATE/bug_report.doctree
docs/.doctrees/.github/ISSUE_TEMPLATE/feature_request.doctree
docs/.doctrees/docs/index.doctree
docs/.doctrees/docs/_build/markdown/index.doctree
docs/.github/ISSUE_TEMPLATE/bug_report.html
docs/.github/ISSUE_TEMPLATE/feature_request.html
docs/_sources/CONTRIBUTING.md.txt
docs/_sources/README.md.txt
docs/_sources/index.rst.txt
docs/_sources/.github/ISSUE_TEMPLATE/bug_report.md.txt
docs/_sources/.github/ISSUE_TEMPLATE/feature_request.md.txt
docs/_sources/docs/_build/markdown/index.md.txt
docs/docs/.buildinfo
docs/docs/genindex.html
docs/docs/index.html
docs/docs/objects.inv
docs/docs/py-modindex.html
docs/docs/search.html
docs/docs/searchindex.js
docs/docs/.doctrees/environment.pickle
docs/docs/.doctrees/index.doctree
docs/docs/_sources/index.rst.txt
src/test.py
src/fin_libs/__init__.py
src/fin_libs.egg-info/PKG-INFO
src/fin_libs.egg-info/SOURCES.txt
src/fin_libs.egg-info/dependency_links.txt
src/fin_libs.egg-info/requires.txt
src/fin_libs.egg-info/top_level.txt
src/fin_libs/compound_annual_growth_rate/__init__.py
src/fin_libs/dividends/__init__.py
src/fin_libs/eps/__init__.py
src/fin_libs/income/__init__.py
src/fin_libs/interest/__init__.py
src/fin_libs/interest/compound/__init__.py
src/fin_libs/interest/simple/__init__.py
src/fin_libs/linear_least_squares/__init__.py
src/fin_libs/price/__init__.py
src/fin_libs/weighted_average/__init__.py