Metadata-Version: 2.1
Name: fin-libs
Version: 0.2.0
Summary: Python library that exposes tools for financial analytics
License:                                  Apache License
Project-URL: repository, https://github.com/azepecki/fin-libs
Platform: UNKNOWN
Requires-Python: >=3.9
Provides-Extra: develop
License-File: LICENSE
